fitz_ai/__init__.py
fitz_ai/api/__init__.py
fitz_ai/api/app.py
fitz_ai/api/dependencies.py
fitz_ai/api/models/__init__.py
fitz_ai/api/models/schemas.py
fitz_ai/api/routes/__init__.py
fitz_ai/api/routes/collections.py
fitz_ai/api/routes/health.py
fitz_ai/api/routes/ingest.py
fitz_ai/api/routes/query.py
fitz_ai/backends/__init__.py
fitz_ai/backends/local_llm/__init__.py
fitz_ai/backends/local_llm/chat.py
fitz_ai/backends/local_llm/embedding.py
fitz_ai/backends/local_llm/rerank.py
fitz_ai/backends/local_llm/runtime.py
fitz_ai/backends/local_vector_db/__init__.py
fitz_ai/backends/local_vector_db/config.py
fitz_ai/backends/local_vector_db/faiss.py
fitz_ai/backends/local_vector_db/runtime.py
fitz_ai/cli/__init__.py
fitz_ai/cli/cli.py
fitz_ai/cli/context.py
fitz_ai/cli/utils.py
fitz_ai/cli/commands/__init__.py
fitz_ai/cli/commands/chat.py
fitz_ai/cli/commands/collections.py
fitz_ai/cli/commands/config.py
fitz_ai/cli/commands/doctor.py
fitz_ai/cli/commands/engine.py
fitz_ai/cli/commands/ingest.py
fitz_ai/cli/commands/init.py
fitz_ai/cli/commands/keywords.py
fitz_ai/cli/commands/map.py
fitz_ai/cli/commands/plugin.py
fitz_ai/cli/commands/query.py
fitz_ai/cli/commands/quickstart.py
fitz_ai/cli/commands/serve.py
fitz_ai/cli/ui/__init__.py
fitz_ai/cli/ui/console.py
fitz_ai/cli/ui/display.py
fitz_ai/cli/ui/engine_selection.py
fitz_ai/cli/ui/output.py
fitz_ai/cli/ui/progress.py
fitz_ai/cli/ui/prompts.py
fitz_ai/config/__init__.py
fitz_ai/config/loader.py
fitz_ai/core/__init__.py
fitz_ai/core/answer.py
fitz_ai/core/answer_mode.py
fitz_ai/core/answer_mode_resolver.py
fitz_ai/core/chunk.py
fitz_ai/core/config.py
fitz_ai/core/conflicts.py
fitz_ai/core/constraints.py
fitz_ai/core/detect.py
fitz_ai/core/document.py
fitz_ai/core/engine.py
fitz_ai/core/exceptions.py
fitz_ai/core/http.py
fitz_ai/core/instrumentation.py
fitz_ai/core/knowledge.py
fitz_ai/core/paths.py
fitz_ai/core/provenance.py
fitz_ai/core/query.py
fitz_ai/core/registry.py
fitz_ai/core/utils.py
fitz_ai-0.5.1.dist-info/licenses/LICENSE
fitz_ai-0.5.1.dist-info/METADATA
fitz_ai-0.5.1.dist-info/WHEEL
fitz_ai-0.5.1.dist-info/entry_points.txt
fitz_ai-0.5.1.dist-info/top_level.txt
fitz_ai-0.5.1.dist-info/RECORD
