Metadata-Version: 2.4
Name: fitz-ai
Version: 0.5.1
Summary: A modular, production-ready knowledge engine platform with clean architecture and multi-paradigm support (RAG, CLaRa).
Author: Yan Fitzner
License: MIT
Project-URL: Homepage, https://github.com/yafitzdev/fitz-ai
Project-URL: Repository, https://github.com/yafitzdev/fitz-ai
Project-URL: Documentation, https://github.com/yafitzdev/fitz-ai#readme
Project-URL: Issues, https://github.com/yafitzdev/fitz-ai/issues
Project-URL: Changelog, https://github.com/yafitzdev/fitz-ai/blob/main/CHANGELOG.md
Project-URL: Source Code, https://github.com/yafitzdev/fitz-ai
Keywords: rag,retrieval,augmented,generation,llm,ai,knowledge-base,vector-database,semantic-search,document-processing,embeddings,nlp,clara,compression,machine-learning
Classifier: Development Status :: 4 - Beta
Classifier: Intended Audience :: Developers
Classifier: Intended Audience :: Science/Research
Classifier: License :: OSI Approved :: MIT License
Classifier: Operating System :: OS Independent
Classifier: Programming Language :: Python :: 3
Classifier: Programming Language :: Python :: 3.10
Classifier: Programming Language :: Python :: 3.11
Classifier: Programming Language :: Python :: 3.12
Classifier: Programming Language :: Python :: 3 :: Only
Classifier: Topic :: Software Development :: Libraries :: Python Modules
Classifier: Topic :: Scientific/Engineering :: Artificial Intelligence
Classifier: Topic :: Text Processing :: Indexing
Classifier: Topic :: Database
Classifier: Typing :: Typed
Requires-Python: >=3.10
License-File: LICENSE
Requires-Dist: pydantic>=2.0
Requires-Dist: pyyaml>=6.0
Requires-Dist: httpx>=0.24
Requires-Dist: typing-extensions>=4.7
Requires-Dist: typer>=0.9
Requires-Dist: jinja2>=3.1
Requires-Dist: faiss-cpu>=1.7.0
Requires-Dist: docling>=2.0
Provides-Extra: local
Requires-Dist: ollama>=0.1.0; extra == "local"
Provides-Extra: map
Requires-Dist: umap-learn>=0.5.0; extra == "map"
Requires-Dist: scikit-learn>=1.0; extra == "map"
Provides-Extra: remote
Requires-Dist: qdrant-client>=1.7; extra == "remote"
Provides-Extra: clara
Requires-Dist: torch>=2.0; extra == "clara"
Requires-Dist: transformers>=4.35; extra == "clara"
Requires-Dist: accelerate>=0.24; extra == "clara"
Requires-Dist: bitsandbytes>=0.41; extra == "clara"
Requires-Dist: peft>=0.10; extra == "clara"
Provides-Extra: api
Requires-Dist: fastapi>=0.100.0; extra == "api"
Requires-Dist: uvicorn[standard]>=0.23.0; extra == "api"
Provides-Extra: dev
Requires-Dist: pytest>=7.0; extra == "dev"
Requires-Dist: pytest-cov>=4.0; extra == "dev"
Requires-Dist: black>=23.0; extra == "dev"
Requires-Dist: isort>=5.0; extra == "dev"
Requires-Dist: mypy>=1.0; extra == "dev"
Requires-Dist: ruff>=0.1.0; extra == "dev"
Provides-Extra: all
Requires-Dist: ollama>=0.1.0; extra == "all"
Requires-Dist: qdrant-client>=1.7; extra == "all"
Requires-Dist: umap-learn>=0.5.0; extra == "all"
Requires-Dist: scikit-learn>=1.0; extra == "all"
Requires-Dist: fastapi>=0.100.0; extra == "all"
Requires-Dist: uvicorn[standard]>=0.23.0; extra == "all"
Requires-Dist: torch>=2.0; extra == "all"
Requires-Dist: transformers>=4.35; extra == "all"
Requires-Dist: accelerate>=0.24; extra == "all"
Requires-Dist: bitsandbytes>=0.41; extra == "all"
Requires-Dist: peft>=0.10; extra == "all"
Dynamic: license-file
